{
  "channels": {
    "日服-测试频道": {"bot": "JP", "channel_id": "1412077043759190117"},
    "日服-官方消息频道": {"bot": "JP", "channel_id": "1244898075135311893"},
    "日服-策划面对面频道": {"bot": "JP", "channel_id": "1320665511478038608"},
    "日服-公告发布频道": {"bot": "JP", "channel_id": "1238410997421838389"},
    "繁中服-测试频道": {"bot": "TC", "channel_id": "1435902837921021962"},
    "繁中服-甜梅爆料所": {"bot": "TC", "channel_id": "1236864636066725961"},
    "繁中服-重要通告": {"bot": "TC", "channel_id": "1247850957715275806"},
    "东南亚服-测试频道": {"bot": "SEA", "channel_id": "1514193499363217428"},
    "英-web商城频道": {"bot": "SEA", "channel_id": "1320970432819757066"},
    "越-web商城频道": {"bot": "SEA", "channel_id": "1320738587880325131"},
    "泰-web商城频道": {"bot": "SEA", "channel_id": "1321004965879087134"},
    "英-公告发布频道": {"bot": "SEA", "channel_id": "1250016998721716224"},
    "越-公告发布频道": {"bot": "SEA", "channel_id": "1320737963142942720"},
    "泰-公告发布频道": {"bot": "SEA", "channel_id": "1237222851808071680"},
    "英-日常宣发频道": {"bot": "SEA", "channel_id": "1260136353493024830"},
    "越-日常宣发频道": {"bot": "SEA", "channel_id": "1240917748184383550"},
    "泰-日常宣发频道": {"bot": "SEA", "channel_id": "1240916452463083580"},
    "英-时装宣发频道": {"bot": "SEA", "channel_id": "1240915828724072479"},
    "越-时装宣发频道": {"bot": "SEA", "channel_id": "1240917842023677982"},
    "泰-时装宣发频道": {"bot": "SEA", "channel_id": "1240916568280403989"},
    "韩服-测试频道": {"bot": "KR", "channel_id": "1508721766606962759"},
    "韩服-版本更新频道": {"bot": "KR", "channel_id": "1265554715953991804"},
    "韩服-内容发布频道": {"bot": "KR", "channel_id": "1268424735214145600"},
    "韩服-活动发布频道": {"bot": "KR", "channel_id": "1268424101962186905"}
  }
}